{
    "mode": "client",
    "user_id": "test",
    "password": "12345",
    "ip": "localhost",
    "mysql_username": "root",
    "mysql_port": 3306,
    "mysql_password": "751224",
    "socket_port": 46364,
    "database": "test",
    "key_search": [
        "datadescribe",
        "experimentdate",
        "dataformat",
        "samplehospital",
        "sampleid",
        "sampledescribe",
        "sampletype",
        "samplemethod",
        "diseasename",
        "diseasetype",
        "wavelength",
        "power",
        "filter",
        "fov",
        "shootnum",
        "zslice",
        "matchsize"
    ],
    "key_show": [
        [
            "id",
            "int"
        ],
        [
            "pid",
            "int"
        ],
        [
            "datanum",
            "varchar"
        ],
        [
            "dealtimes",
            "int"
        ],
        [
            "uploader",
            "int"
        ],
        [
            "uploadstartdate",
            "datetime"
        ],
        [
            "uploadenddate",
            "datetime"
        ],
        [
            "datadescribe",
            "text"
        ],
        [
            "experimentdate",
            "datetime"
        ],
        [
            "dataformat",
            "varchar"
        ],
        [
            "samplehospital",
            "varchar"
        ],
        [
            "sampleid",
            "varchar"
        ],
        [
            "sampledescribe",
            "varchar"
        ],
        [
            "sampletype",
            "varchar"
        ],
        [
            "samplemethod",
            "varchar"
        ],
        [
            "diseasename",
            "varchar"
        ],
        [
            "diseasetype",
            "datetime"
        ],
        [
            "wavelength",
            "int"
        ],
        [
            "power",
            "int"
        ],
        [
            "filter",
            "varchar"
        ],
        [
            "fov",
            "varchar"
        ],
        [
            "shootnum",
            "int"
        ],
        [
            "zslice",
            "varchar"
        ],
        [
            "matchsize",
            "varchar"
        ]
    ]
}